{
  "sentences": [
    {
      "index": 0,
      "tokens": [
        {
          "index": 1,
          "word": "PER",
          "originalText": "PER",
          "characterOffsetBegin": 2,
          "characterOffsetEnd": 5,
          "before": "",
          "after": " "
        },
        {
          "index": 2,
          "word": "CURIAM",
          "originalText": "CURIAM",
          "characterOffsetBegin": 6,
          "characterOffsetEnd": 12,
          "before": " ",
          "after": ""
        },
        {
          "index": 3,
          "word": ".",
          "originalText": ".",
          "characterOffsetBegin": 12,
          "characterOffsetEnd": 13,
          "before": "",
          "after": ""
        }
      ]
    },
    {
      "index": 1,
      "tokens": [
        {
          "index": 1,
          "word": "If",
          "originalText": "If",
          "characterOffsetBegin": 15,
          "characterOffsetEnd": 17,
          "before": "",
          "after": " "
        },
        {
          "index": 2,
          "word": "the",
          "originalText": "the",
          "characterOffsetBegin": 18,
          "characterOffsetEnd": 21,
          "before": " ",
          "after": " "
        },
        {
          "index": 3,
          "word": "sheriff",
          "originalText": "sheriff",
          "characterOffsetBegin": 22,
          "characterOffsetEnd": 29,
          "before": " ",
          "after": " "
        },
        {
          "index": 4,
          "word": "or",
          "originalText": "or",
          "characterOffsetBegin": 30,
          "characterOffsetEnd": 32,
          "before": " ",
          "after": " "
        },
        {
          "index": 5,
          "word": "marshal",
          "originalText": "marshal",
          "characterOffsetBegin": 33,
          "characterOffsetEnd": 40,
          "before": " ",
          "after": " "
        },
        {
          "index": 6,
          "word": "seizes",
          "originalText": "seizes",
          "characterOffsetBegin": 41,
          "characterOffsetEnd": 47,
          "before": " ",
          "after": " "
        },
        {
          "index": 7,
          "word": "property",
          "originalText": "property",
          "characterOffsetBegin": 48,
          "characterOffsetEnd": 56,
          "before": " ",
          "after": " "
        },
        {
          "index": 8,
          "word": "in",
          "originalText": "in",
          "characterOffsetBegin": 57,
          "characterOffsetEnd": 59,
          "before": " ",
          "after": " "
        },
        {
          "index": 9,
          "word": "execution",
          "originalText": "execution",
          "characterOffsetBegin": 60,
          "characterOffsetEnd": 69,
          "before": " ",
          "after": ""
        },
        {
          "index": 10,
          "word": ",",
          "originalText": ",",
          "characterOffsetBegin": 69,
          "characterOffsetEnd": 70,
          "before": "",
          "after": " "
        },
        {
          "index": 11,
          "word": "and",
          "originalText": "and",
          "characterOffsetBegin": 71,
          "characterOffsetEnd": 74,
          "before": " ",
          "after": " "
        },
        {
          "index": 12,
          "word": "neglects",
          "originalText": "neglects",
          "characterOffsetBegin": 75,
          "characterOffsetEnd": 83,
          "before": " ",
          "after": " "
        },
        {
          "index": 13,
          "word": "to",
          "originalText": "to",
          "characterOffsetBegin": 84,
          "characterOffsetEnd": 86,
          "before": " ",
          "after": " "
        },
        {
          "index": 14,
          "word": "sell",
          "originalText": "sell",
          "characterOffsetBegin": 87,
          "characterOffsetEnd": 91,
          "before": " ",
          "after": " "
        },
        {
          "index": 15,
          "word": "it",
          "originalText": "it",
          "characterOffsetBegin": 92,
          "characterOffsetEnd": 94,
          "before": " ",
          "after": ""
        },
        {
          "index": 16,
          "word": ",",
          "originalText": ",",
          "characterOffsetBegin": 94,
          "characterOffsetEnd": 95,
          "before": "",
          "after": " "
        },
        {
          "index": 17,
          "word": "and",
          "originalText": "and",
          "characterOffsetBegin": 96,
          "characterOffsetEnd": 99,
          "before": " ",
          "after": " "
        },
        {
          "index": 18,
          "word": "is",
          "originalText": "is",
          "characterOffsetBegin": 100,
          "characterOffsetEnd": 102,
          "before": " ",
          "after": " "
        },
        {
          "index": 19,
          "word": "sued",
          "originalText": "sued",
          "characterOffsetBegin": 103,
          "characterOffsetEnd": 107,
          "before": " ",
          "after": " "
        },
        {
          "index": 20,
          "word": "for",
          "originalText": "for",
          "characterOffsetBegin": 108,
          "characterOffsetEnd": 111,
          "before": " ",
          "after": " "
        },
        {
          "index": 21,
          "word": "his",
          "originalText": "his",
          "characterOffsetBegin": 112,
          "characterOffsetEnd": 115,
          "before": " ",
          "after": " "
        },
        {
          "index": 22,
          "word": "neglect",
          "originalText": "neglect",
          "characterOffsetBegin": 116,
          "characterOffsetEnd": 123,
          "before": " ",
          "after": ""
        },
        {
          "index": 23,
          "word": ",",
          "originalText": ",",
          "characterOffsetBegin": 123,
          "characterOffsetEnd": 124,
          "before": "",
          "after": " "
        },
        {
          "index": 24,
          "word": "the",
          "originalText": "the",
          "characterOffsetBegin": 125,
          "characterOffsetEnd": 128,
          "before": " ",
          "after": " "
        },
        {
          "index": 25,
          "word": "plaintiff-shall",
          "originalText": "plaintiff-shall",
          "characterOffsetBegin": 129,
          "characterOffsetEnd": 144,
          "before": " ",
          "after": " "
        },
        {
          "index": 26,
          "word": "recover",
          "originalText": "recover",
          "characterOffsetBegin": 145,
          "characterOffsetEnd": 152,
          "before": " ",
          "after": " "
        },
        {
          "index": 27,
          "word": "damages",
          "originalText": "damages",
          "characterOffsetBegin": 153,
          "characterOffsetEnd": 160,
          "before": " ",
          "after": " "
        },
        {
          "index": 28,
          "word": "to",
          "originalText": "to",
          "characterOffsetBegin": 161,
          "characterOffsetEnd": 163,
          "before": " ",
          "after": " "
        },
        {
          "index": 29,
          "word": "the",
          "originalText": "the",
          "characterOffsetBegin": 164,
          "characterOffsetEnd": 167,
          "before": " ",
          "after": " "
        },
        {
          "index": 30,
          "word": "amount",
          "originalText": "amount",
          "characterOffsetBegin": 168,
          "characterOffsetEnd": 174,
          "before": " ",
          "after": " "
        },
        {
          "index": 31,
          "word": "of",
          "originalText": "of",
          "characterOffsetBegin": 175,
          "characterOffsetEnd": 177,
          "before": " ",
          "after": " "
        },
        {
          "index": 32,
          "word": "what",
          "originalText": "what",
          "characterOffsetBegin": 178,
          "characterOffsetEnd": 182,
          "before": " ",
          "after": " "
        },
        {
          "index": 33,
          "word": "the",
          "originalText": "the",
          "characterOffsetBegin": 183,
          "characterOffsetEnd": 186,
          "before": " ",
          "after": " "
        },
        {
          "index": 34,
          "word": "property",
          "originalText": "property",
          "characterOffsetBegin": 187,
          "characterOffsetEnd": 195,
          "before": " ",
          "after": " "
        },
        {
          "index": 35,
          "word": "would",
          "originalText": "would",
          "characterOffsetBegin": 196,
          "characterOffsetEnd": 201,
          "before": " ",
          "after": " "
        },
        {
          "index": 36,
          "word": "have",
          "originalText": "have",
          "characterOffsetBegin": 202,
          "characterOffsetEnd": 206,
          "before": " ",
          "after": " "
        },
        {
          "index": 37,
          "word": "produced",
          "originalText": "produced",
          "characterOffsetBegin": 207,
          "characterOffsetEnd": 215,
          "before": " ",
          "after": " "
        },
        {
          "index": 38,
          "word": "had",
          "originalText": "had",
          "characterOffsetBegin": 216,
          "characterOffsetEnd": 219,
          "before": " ",
          "after": " "
        },
        {
          "index": 39,
          "word": "he",
          "originalText": "he",
          "characterOffsetBegin": 220,
          "characterOffsetEnd": 222,
          "before": " ",
          "after": " "
        },
        {
          "index": 40,
          "word": "sold",
          "originalText": "sold",
          "characterOffsetBegin": 223,
          "characterOffsetEnd": 227,
          "before": " ",
          "after": " "
        },
        {
          "index": 41,
          "word": "it",
          "originalText": "it",
          "characterOffsetBegin": 228,
          "characterOffsetEnd": 230,
          "before": " ",
          "after": ""
        }
      ]
    }
  ]
}